timelycli/__main__.py
timelycli-0.1.0.dist-info/METADATA
timelycli-0.1.0.dist-info/WHEEL
timelycli-0.1.0.dist-info/entry_points.txt
timelycli-0.1.0.dist-info/RECORD
