Metadata-Version: 2.4
Name: timelycli
Version: 0.1.0
Summary: A CLI tool to display current date and time
Author-email: Your Name <you@example.com>
License: MIT
Requires-Python: >=3.7
Requires-Dist: pytz
Requires-Dist: tzlocal
